openinference/instrumentation/openlit/__init__.py
openinference/instrumentation/openlit/_span_processor.py
openinference/instrumentation/openlit/py.typed
openinference/instrumentation/openlit/version.py
openinference_instrumentation_openlit-0.1.2.dist-info/METADATA
openinference_instrumentation_openlit-0.1.2.dist-info/WHEEL
openinference_instrumentation_openlit-0.1.2.dist-info/licenses/LICENSE
openinference_instrumentation_openlit-0.1.2.dist-info/RECORD
