Metadata-Version: 2.4
Name: openinference-instrumentation-openlit
Version: 0.1.2
Summary: OpenInference OpenLIT Instrumentation
Project-URL: Homepage, https://github.com/Arize-ai/openinference/tree/main/python/instrumentation/openinference-instrumentation-openlit
Author-email: OpenInference Authors <oss@arize.com>
License-Expression: Apache-2.0
License-File: LICENSE
Classifier: Development Status :: 5 - Production/Stable
Classifier: Intended Audience :: Developers
Classifier: License :: OSI Approved :: Apache Software License
Classifier: Programming Language :: Python
Classifier: Programming Language :: Python :: 3
Classifier: Programming Language :: Python :: 3.9
Classifier: Programming Language :: Python :: 3.10
Classifier: Programming Language :: Python :: 3.11
Classifier: Programming Language :: Python :: 3.12
Classifier: Programming Language :: Python :: 3.13
Requires-Python: <3.14,>=3.9
Requires-Dist: openinference-instrumentation>=0.1.34
Requires-Dist: openinference-semantic-conventions>=0.1.21
Requires-Dist: opentelemetry-sdk>=1.20.0
Requires-Dist: opentelemetry-semantic-conventions-ai>=0.4.9
Provides-Extra: test
Requires-Dist: openlit>=1.0.0; extra == 'test'
Requires-Dist: opentelemetry-exporter-otlp-proto-http; extra == 'test'
Requires-Dist: opentelemetry-sdk>=1.20.0; extra == 'test'
Requires-Dist: pytest-recording; extra == 'test'
Requires-Dist: semantic-kernel>=1.0.0; extra == 'test'
